AUTHORS
COPYING
MANIFEST.in
setup.py
sigasync/__init__.py
sigasync/configspec.ini
sigasync/dispatcher.py
sigasync/http.py
sigasync/models.py
sigasync/sigasync_handler.py
sigasync/sigasync_spooler.py
sigasync/signal_connection.py
sigasync/spooler.py
sigasync/tests.py
sigasync/urls.py
sigasync/views.py
spooler.egg-info/PKG-INFO
spooler.egg-info/SOURCES.txt
spooler.egg-info/dependency_links.txt
spooler.egg-info/requires.txt
spooler.egg-info/top_level.txt