Metadata-Version: 1.0
Name: spooler
Version: 0.04
Summary: Simple task queue using the filesystem
Home-page: http://github.com/woome/spooler
Author: Woome
Author-email: patrick@woome.com
License: GNU GPL v3
Download-URL: http://github.com/woome/spooler/tarball/master
Keywords: asynchronous,queue,task queue
Platform: any
Classifier: Development Status :: 4 - Beta
Classifier: Intended Audience :: Developers
Classifier: License :: OSI Approved :: GNU General Public License (GPL)
Classifier: Operating System :: POSIX
Classifier: Programming Language :: Python
